{
  "$id": "p129550",
  "$schema": "https://schema.yext.com/config/km/entity/v1",
  "primaryLocale": "en",
  "content": {
    "c_category": "Ale",
    "c_maxPrice": "18.99",
    "c_minPrice": "13.73",
    "c_numberReviews": "8",
    "c_priceRange": "$13.73 - $18.99",
    "c_subCategory": "IPA",
    "c_type": "Imperial Double IPA",
    "landingPageUrl": "https://drizly.com/beer/ale/ipa/imperial-double-ipa/scofflaw-brewing-company-pog-basement-ipa-double-jeopardy-double-ipa/p129550",
    "name": "Scofflaw Brewing Company POG Basement IPA Double Jeopardy Double IPA",
    "photoGallery": [
      {
        "image": {
          "height": 480,
          "sourceUrl": "https://products1.imgix.drizly.com/ci-scofflaw-double-jeopardy-double-ipa-4925b7c28850d15f.png?auto\u003dformat%2Ccompress\u0026ch\u003dWidth%2CDPR\u0026dpr\u003d2\u0026fm\u003djpg\u0026h\u003d240\u0026q\u003d20",
          "thumbnails": [
            {
              "height": 480,
              "url": "https://a.mktgcdn.com/p-sandbox/GHhBNIV8Ubgp7V_4HbLZNwGSyXYvCeDQG6Rke_RjkjU/320x480.jpg",
              "width": 320
            },
            {
              "height": 450,
              "url": "https://a.mktgcdn.com/p-sandbox/GHhBNIV8Ubgp7V_4HbLZNwGSyXYvCeDQG6Rke_RjkjU/300x450.jpg",
              "width": 300
            },
            {
              "height": 294,
              "url": "https://a.mktgcdn.com/p-sandbox/GHhBNIV8Ubgp7V_4HbLZNwGSyXYvCeDQG6Rke_RjkjU/196x294.jpg",
              "width": 196
            }
          ],
          "url": "https://a.mktgcdn.com/p-sandbox/GHhBNIV8Ubgp7V_4HbLZNwGSyXYvCeDQG6Rke_RjkjU/320x480.jpg",
          "width": 320
        }
      }
    ]
  },
  "entityType": "ce_beer",
  "labels": []
}