{
  "$id": "p164076",
  "$schema": "https://schema.yext.com/config/km/entity/v1",
  "primaryLocale": "en",
  "content": {
    "c_category": "Specialty Beer Alternatives",
    "c_maxPrice": "33.77",
    "c_minPrice": "11.99",
    "c_numberReviews": "15",
    "c_priceRange": "$11.99 - $33.77",
    "c_subCategory": "Hard Seltzer",
    "landingPageUrl": "https://drizly.com/beer/specialty-beer-alternatives/hard-seltzer/truly-lemonade-freeze-pop-variety-pack/p164076",
    "name": "Truly Lemonade Freeze Pop Variety Pack"
  },
  "entityType": "ce_beer",
  "labels": []
}