{
  "$id": "p16680",
  "$schema": "https://schema.yext.com/config/km/entity/v1",
  "primaryLocale": "en",
  "content": {
    "c_category": "Champagne Sparkling Wine",
    "c_maxPrice": "849.99",
    "c_minPrice": "1.00",
    "c_numberReviews": "2",
    "c_priceRange": "$1.00 - $849.99",
    "c_subCategory": "Sparkling Rose Wine",
    "landingPageUrl": "https://drizly.com/wine/champagne-sparkling-wine/sparkling-rose-wine/armand-de-brignac-ace-of-spades-rose/p16680",
    "name": "Armand De Brignac Ace of Spades Rose Champagne"
  },
  "entityType": "ce_wine",
  "labels": []
}