{
  "$id": "p2155",
  "$schema": "https://schema.yext.com/config/km/entity/v1",
  "primaryLocale": "en",
  "content": {
    "c_category": "Red Wine",
    "c_maxPrice": "1100.00",
    "c_minPrice": "3.99",
    "c_numberReviews": "706",
    "c_priceRange": "$3.99 - $1100.00",
    "c_subCategory": "Cabernet Sauvignon",
    "landingPageUrl": "https://drizly.com/wine/red-wine/cabernet-sauvignon/woodbridge-cabernet-sauvignon-red-wine-by-robert-mondavi/p2155",
    "name": "Woodbridge Cabernet Sauvignon Red Wine by Robert Mondavi"
  },
  "entityType": "ce_wine",
  "labels": []
}