{
  "$id": "p2227",
  "$schema": "https://schema.yext.com/config/km/entity/v1",
  "primaryLocale": "en",
  "content": {
    "c_category": "Rum",
    "c_maxPrice": "99.99",
    "c_minPrice": "22.96",
    "c_numberReviews": "130",
    "c_priceRange": "$22.96 - $99.99",
    "c_subCategory": "Aged Rum",
    "landingPageUrl": "https://drizly.com/liquor/rum/aged-rum/ron-zacapa-no-23-rum/p2227",
    "name": "Ron Zacapa No. 23 Rum",
    "photoGallery": [
      {
        "image": {
          "height": 480,
          "sourceUrl": "https://products0.imgix.drizly.com/ci-ron-zacapa-centenario-23-year-ed03ac34ff638d41.jpeg?auto\u003dformat%2Ccompress\u0026ch\u003dWidth%2CDPR\u0026dpr\u003d2\u0026fm\u003djpg\u0026h\u003d240\u0026q\u003d20",
          "thumbnails": [
            {
              "height": 480,
              "url": "https://a.mktgcdn.com/p-sandbox/uB0YKOApVhPVI-iWhavz-w4hJZklY3I5NfoPjngfpxc/320x480.jpg",
              "width": 320
            },
            {
              "height": 450,
              "url": "https://a.mktgcdn.com/p-sandbox/uB0YKOApVhPVI-iWhavz-w4hJZklY3I5NfoPjngfpxc/300x450.jpg",
              "width": 300
            },
            {
              "height": 294,
              "url": "https://a.mktgcdn.com/p-sandbox/uB0YKOApVhPVI-iWhavz-w4hJZklY3I5NfoPjngfpxc/196x294.jpg",
              "width": 196
            }
          ],
          "url": "https://a.mktgcdn.com/p-sandbox/uB0YKOApVhPVI-iWhavz-w4hJZklY3I5NfoPjngfpxc/320x480.jpg",
          "width": 320
        }
      }
    ]
  },
  "entityType": "ce_liquor",
  "labels": []
}