{
  "$id": "p23366",
  "$schema": "https://schema.yext.com/config/km/entity/v1",
  "primaryLocale": "en",
  "content": {
    "c_category": "Red Wine",
    "c_maxPrice": "20.15",
    "c_minPrice": "4.19",
    "c_numberReviews": "6",
    "c_priceRange": "$4.19 - $20.15",
    "c_subCategory": "Malbec",
    "landingPageUrl": "https://drizly.com/wine/red-wine/malbec/kaiken-estate-malbec/p23366",
    "name": "Kaiken Estate Malbec",
    "photoGallery": [
      {
        "image": {
          "height": 480,
          "sourceUrl": "https://products2.imgix.drizly.com/ci-kaiken-malbec-2012-448cfd4a717b7a8d.jpeg?auto\u003dformat%2Ccompress\u0026ch\u003dWidth%2CDPR\u0026dpr\u003d2\u0026fm\u003djpg\u0026h\u003d240\u0026q\u003d20",
          "thumbnails": [
            {
              "height": 480,
              "url": "https://a.mktgcdn.com/p-sandbox/JMlb9g2Q9IAVl13HYjlsL2qnnRwxpHoXEMx9LBmzPJY/320x480.jpg",
              "width": 320
            },
            {
              "height": 450,
              "url": "https://a.mktgcdn.com/p-sandbox/JMlb9g2Q9IAVl13HYjlsL2qnnRwxpHoXEMx9LBmzPJY/300x450.jpg",
              "width": 300
            },
            {
              "height": 294,
              "url": "https://a.mktgcdn.com/p-sandbox/JMlb9g2Q9IAVl13HYjlsL2qnnRwxpHoXEMx9LBmzPJY/196x294.jpg",
              "width": 196
            }
          ],
          "url": "https://a.mktgcdn.com/p-sandbox/JMlb9g2Q9IAVl13HYjlsL2qnnRwxpHoXEMx9LBmzPJY/320x480.jpg",
          "width": 320
        }
      }
    ]
  },
  "entityType": "ce_wine",
  "labels": []
}