{
  "$id": "p87930",
  "$schema": "https://schema.yext.com/config/km/entity/v1",
  "primaryLocale": "en",
  "content": {
    "c_category": "Red Wine",
    "c_maxPrice": "53.89",
    "c_minPrice": "9.95",
    "c_numberReviews": "16",
    "c_priceRange": "$9.95 - $53.89",
    "c_subCategory": "Cabernet Sauvignon",
    "landingPageUrl": "https://drizly.com/wine/red-wine/cabernet-sauvignon/josh-cellars-reserve-lodi-cabernet-sauvignon/p87930",
    "name": "Josh Cellars Reserve Lodi Cabernet Sauvignon",
    "photoGallery": [
      {
        "image": {
          "height": 480,
          "sourceUrl": "https://products2.imgix.drizly.com/ci-josh-cellars-reserve-gratitude-cabernet-sauvignon-bddbc23417647a77.jpeg?auto\u003dformat%2Ccompress\u0026ch\u003dWidth%2CDPR\u0026dpr\u003d2\u0026fm\u003djpg\u0026h\u003d240\u0026q\u003d20",
          "thumbnails": [
            {
              "height": 480,
              "url": "https://a.mktgcdn.com/p-sandbox/IStBShhxCIHfCeYxsvIQVM4Nw58ov-NYJw2mCdeYfbE/320x480.jpg",
              "width": 320
            },
            {
              "height": 450,
              "url": "https://a.mktgcdn.com/p-sandbox/IStBShhxCIHfCeYxsvIQVM4Nw58ov-NYJw2mCdeYfbE/300x450.jpg",
              "width": 300
            },
            {
              "height": 294,
              "url": "https://a.mktgcdn.com/p-sandbox/IStBShhxCIHfCeYxsvIQVM4Nw58ov-NYJw2mCdeYfbE/196x294.jpg",
              "width": 196
            }
          ],
          "url": "https://a.mktgcdn.com/p-sandbox/IStBShhxCIHfCeYxsvIQVM4Nw58ov-NYJw2mCdeYfbE/320x480.jpg",
          "width": 320
        }
      }
    ]
  },
  "entityType": "ce_wine",
  "labels": []
}