{
  "$id": "p92167",
  "$schema": "https://schema.yext.com/config/km/entity/v1",
  "primaryLocale": "en",
  "content": {
    "c_category": "Specialty Beer Alternatives",
    "c_maxPrice": "17.99",
    "c_minPrice": "7.49",
    "c_numberReviews": "7",
    "c_priceRange": "$7.49 - $17.99",
    "c_subCategory": "Non Alcoholic Beer",
    "landingPageUrl": "https://drizly.com/beer/specialty-beer-alternatives/non-alcoholic-beer/wellbeing-heavenly-body-non-alcoholic-golden-wheat/p92167",
    "name": "Wellbeing Heavenly Body Non-Alcoholic Golden Wheat",
    "photoGallery": [
      {
        "image": {
          "height": 480,
          "sourceUrl": "https://products2.imgix.drizly.com/ci-wellbeing-heavenly-body-non-alcoholic-golden-wheat-03727b2b577ec9df.png?auto\u003dformat%2Ccompress\u0026ch\u003dWidth%2CDPR\u0026dpr\u003d2\u0026fm\u003djpg\u0026h\u003d240\u0026q\u003d20",
          "thumbnails": [
            {
              "height": 480,
              "url": "https://a.mktgcdn.com/p-sandbox/1PJXqwSj22QIXANHXoZqZePeBJ7Pm_kFJIovEei1Qp4/320x480.jpg",
              "width": 320
            },
            {
              "height": 450,
              "url": "https://a.mktgcdn.com/p-sandbox/1PJXqwSj22QIXANHXoZqZePeBJ7Pm_kFJIovEei1Qp4/300x450.jpg",
              "width": 300
            },
            {
              "height": 294,
              "url": "https://a.mktgcdn.com/p-sandbox/1PJXqwSj22QIXANHXoZqZePeBJ7Pm_kFJIovEei1Qp4/196x294.jpg",
              "width": 196
            }
          ],
          "url": "https://a.mktgcdn.com/p-sandbox/1PJXqwSj22QIXANHXoZqZePeBJ7Pm_kFJIovEei1Qp4/320x480.jpg",
          "width": 320
        }
      }
    ]
  },
  "entityType": "ce_beer",
  "labels": []
}