{
  "$id": "p95766",
  "$schema": "https://schema.yext.com/config/km/entity/v1",
  "primaryLocale": "en",
  "content": {
    "c_category": "Specialty Beer Alternatives",
    "c_maxPrice": "17.99",
    "c_minPrice": "5.95",
    "c_numberReviews": "261",
    "c_priceRange": "$5.95 - $17.99",
    "c_subCategory": "Malt Liquor",
    "landingPageUrl": "https://drizly.com/beer/specialty-beer-alternatives/malt-liquor/pabst-blue-ribbon-hard-coffee/p95766",
    "name": "Pabst Blue Ribbon Hard Coffee",
    "photoGallery": [
      {
        "image": {
          "height": 480,
          "sourceUrl": "https://products1.imgix.drizly.com/ci-pabst-blue-ribbon-hard-coffee-be15c8b5b96ff099.png?auto\u003dformat%2Ccompress\u0026ch\u003dWidth%2CDPR\u0026dpr\u003d2\u0026fm\u003djpg\u0026h\u003d240\u0026q\u003d20",
          "thumbnails": [
            {
              "height": 480,
              "url": "https://a.mktgcdn.com/p-sandbox/SrOa524QmwpaBEJxqbkLMP0DtQVeSSVCdLq52031gaA/320x480.jpg",
              "width": 320
            },
            {
              "height": 450,
              "url": "https://a.mktgcdn.com/p-sandbox/SrOa524QmwpaBEJxqbkLMP0DtQVeSSVCdLq52031gaA/300x450.jpg",
              "width": 300
            },
            {
              "height": 294,
              "url": "https://a.mktgcdn.com/p-sandbox/SrOa524QmwpaBEJxqbkLMP0DtQVeSSVCdLq52031gaA/196x294.jpg",
              "width": 196
            }
          ],
          "url": "https://a.mktgcdn.com/p-sandbox/SrOa524QmwpaBEJxqbkLMP0DtQVeSSVCdLq52031gaA/320x480.jpg",
          "width": 320
        }
      }
    ]
  },
  "entityType": "ce_beer",
  "labels": []
}